craft_parts/__init__.py
craft_parts/__main__.py
craft_parts/_version.py
craft_parts/actions.py
craft_parts/callbacks.py
craft_parts/constraints.py
craft_parts/ctl.py
craft_parts/dirs.py
craft_parts/errors.py
craft_parts/features.py
craft_parts/filesystem_mounts.py
craft_parts/infos.py
craft_parts/lifecycle_manager.py
craft_parts/main.py
craft_parts/parts.py
craft_parts/permissions.py
craft_parts/py.typed
craft_parts/pydantic_schema.py
craft_parts/sequencer.py
craft_parts/steps.py
craft_parts/xattrs.py
craft_parts/executor/__init__.py
craft_parts/executor/collisions.py
craft_parts/executor/environment.py
craft_parts/executor/errors.py
craft_parts/executor/executor.py
craft_parts/executor/filesets.py
craft_parts/executor/migration.py
craft_parts/executor/organize.py
craft_parts/executor/part_handler.py
craft_parts/executor/step_handler.py
craft_parts/overlays/__init__.py
craft_parts/overlays/chroot.py
craft_parts/overlays/errors.py
craft_parts/overlays/layers.py
craft_parts/overlays/overlay_fs.py
craft_parts/overlays/overlay_manager.py
craft_parts/overlays/overlays.py
craft_parts/packages/__init__.py
craft_parts/packages/apt_cache.py
craft_parts/packages/base.py
craft_parts/packages/deb.py
craft_parts/packages/deb_package.py
craft_parts/packages/dnf.py
craft_parts/packages/errors.py
craft_parts/packages/normalize.py
craft_parts/packages/platform.py
craft_parts/packages/snaps.py
craft_parts/packages/yum.py
craft_parts/plugins/__init__.py
craft_parts/plugins/ant_plugin.py
craft_parts/plugins/autotools_plugin.py
craft_parts/plugins/base.py
craft_parts/plugins/cargo_use_plugin.py
craft_parts/plugins/cmake_plugin.py
craft_parts/plugins/dotnet_plugin.py
craft_parts/plugins/dotnet_v2_plugin.py
craft_parts/plugins/dump_plugin.py
craft_parts/plugins/go_plugin.py
craft_parts/plugins/go_use_plugin.py
craft_parts/plugins/gradle_plugin.py
craft_parts/plugins/java_plugin.py
craft_parts/plugins/jlink_plugin.py
craft_parts/plugins/make_plugin.py
craft_parts/plugins/maven_plugin.py
craft_parts-2.28.0.dist-info/licenses/LICENSE
craft_parts-2.28.0.dist-info/METADATA
craft_parts-2.28.0.dist-info/WHEEL
craft_parts-2.28.0.dist-info/entry_points.txt
craft_parts-2.28.0.dist-info/top_level.txt
craft_parts-2.28.0.dist-info/RECORD
