Metadata-Version: 2.4
Name: craft-parts
Version: 2.28.0
Summary: Craft parts tooling
Author-email: "Canonical Ltd." <snapcraft@lists.snapcraft.io>
Project-URL: Homepage, https://github.com/canonical/craft-parts
Classifier: Development Status :: 5 - Production/Stable
Classifier: Intended Audience :: Developers
Classifier: Natural Language :: English
Classifier: Programming Language :: Python :: 3.10
Classifier: Programming Language :: Python :: 3.11
Classifier: Programming Language :: Python :: 3.12
Requires-Python: >=3.10
License-File: LICENSE
Requires-Dist: lxml>=5.3.0
Requires-Dist: pydantic>=2.0.0
Requires-Dist: pyxdg
Requires-Dist: PyYAML
Requires-Dist: requests-unixsocket2>=0.4.0
Requires-Dist: requests<3.0,>=2.32.4
Requires-Dist: semver>=3.0.4
Requires-Dist: tomli>=1.1.0; python_version < "3.11"
Dynamic: license-file
